Scrapetsy/__init__.py
Scrapetsy-0.0.1.dist-info/LICENSE
Scrapetsy-0.0.1.dist-info/METADATA
Scrapetsy-0.0.1.dist-info/WHEEL
Scrapetsy-0.0.1.dist-info/top_level.txt
Scrapetsy-0.0.1.dist-info/RECORD
