Metadata-Version: 2.1
Name: Scrapetsy
Version: 0.0.1
Summary: Scrape product details from www.etsy.com
Author-email: mharitzr <harits.muhammad.only@gmail.com>
Project-URL: Homepage, https://github.com/HaritsAcheiz/Scrapetsy
Classifier: Programming Language :: Python :: 3
Classifier: License :: OSI Approved :: GNU Affero General Public License v3 or later (AGPLv3+)
Classifier: Operating System :: OS Independent
Classifier: Development Status :: 4 - Beta
Requires-Python: >=3.8
License-File: LICENSE
